gpr_calc/NEB.py
gpr_calc/SO3.py
gpr_calc/calculator.py
gpr_calc/gaussianprocess.py
gpr_calc/utilities.py
gpr_calc/kernels/Dot_mb.py
gpr_calc/kernels/RBF_mb.py
gpr_calc/kernels/_dot_kernel.cpython-311-darwin.so
gpr_calc/kernels/_rbf_kernel.cpython-311-darwin.so
gpr_calc/kernels/base.py
gpr_calc/kernels/dot_kernel.cpp
gpr_calc/kernels/dot_kernel.h
gpr_calc/kernels/dot_kernel.py
gpr_calc/kernels/libdot_builder.py
gpr_calc/kernels/librbf_builder.py
gpr_calc/kernels/rbf_kernel.cpp
gpr_calc/kernels/rbf_kernel.h
gpr_calc/kernels/rbf_kernel.py
gpr_calc-0.0.7.dist-info/licenses/LICENSE
gpr_calc-0.0.7.dist-info/METADATA
gpr_calc-0.0.7.dist-info/WHEEL
gpr_calc-0.0.7.dist-info/top_level.txt
gpr_calc-0.0.7.dist-info/RECORD
