Metadata-Version: 2.4
Name: gpr_calc
Version: 0.0.7
Summary: GPR
License: MIT
Classifier: Programming Language :: Python :: 3
Classifier: License :: OSI Approved :: MIT License
Classifier: Operating System :: OS Independent
Requires-Python: >=3.9.1
License-File: LICENSE
Requires-Dist: cffi>=1.0.0
Requires-Dist: mpi4py>=3.0.3
Requires-Dist: ase>=3.23.0
Requires-Dist: pyxtal>=1.0.5
Dynamic: classifier
Dynamic: description
Dynamic: description-content-type
Dynamic: license
Dynamic: license-file
Dynamic: requires-dist
Dynamic: requires-python
Dynamic: summary
